{"trial_id": "0397", "hyperparameters": {"space": [{"class_name": "Choice", "config": {"name": "activation", "default": "relu", "conditions": [], "values": ["relu", "linear", "softmax", "elu", "tanh", "sigmoid"], "ordered": false}}, {"class_name": "Int", "config": {"name": "first_units", "default": null, "conditions": [], "min_value": 8, "max_value": 64, "step": 5, "sampling": "linear"}}, {"class_name": "Int", "config": {"name": "num_layers", "default": null, "conditions": [], "min_value": 1, "max_value": 3, "step": 1, "sampling": "linear"}}, {"class_name": "Int", "config": {"name": "units_0", "default": null, "conditions": [], "min_value": 8, "max_value": 64, "step": 8, "sampling": "linear"}}, {"class_name": "Int", "config": {"name": "units_1", "default": null, "conditions": [], "min_value": 8, "max_value": 64, "step": 8, "sampling": "linear"}}, {"class_name": "Int", "config": {"name": "units_2", "default": null, "conditions": [], "min_value": 8, "max_value": 64, "step": 8, "sampling": "linear"}}], "values": {"activation": "sigmoid", "first_units": 43, "num_layers": 1, "units_0": 40, "units_1": 8, "units_2": 8, "tuner/epochs": 34, "tuner/initial_epoch": 12, "tuner/bracket": 4, "tuner/round": 3, "tuner/trial_id": "0385"}}, "metrics": {"metrics": {"accuracy": {"direction": "max", "observations": [{"value": [0.7314181327819824], "step": 3}]}, "loss": {"direction": "min", "observations": [{"value": [0.5471662282943726], "step": 3}]}, "val_accuracy": {"direction": "max", "observations": [{"value": [0.7282798886299133], "step": 3}]}, "val_loss": {"direction": "min", "observations": [{"value": [0.5530385971069336], "step": 3}]}}}, "score": 0.7282798886299133, "best_step": 3, "status": "COMPLETED", "message": null}